tok_det_metric/__init__.py
tok_det_metric-1.0.0.dist-info/WHEEL
tok_det_metric-1.0.0.dist-info/METADATA
tok_det_metric-1.0.0.dist-info/RECORD
