Metadata-Version: 2.1
Name: tok-det-metric
Version: 1.0.0
Summary: 
Author: Aneta Melisa Stal
Author-email: melisa@writer.com
Requires-Python: >=3.8,<4.0
Classifier: Programming Language :: Python :: 3
Classifier: Programming Language :: Python :: 3.10
Classifier: Programming Language :: Python :: 3.8
Classifier: Programming Language :: Python :: 3.9
Requires-Dist: datasets (>=2.3.2,<3.0.0)
Requires-Dist: more-itertools (>=8.13.0,<9.0.0)
Requires-Dist: numpy (>=1.23.0,<2.0.0)
Requires-Dist: tqdm (>=4.64.0,<5.0.0)
